jupiterone_pyoneer/__init__.py
jupiterone_pyoneer/entities.py
jupiterone_pyoneer/jupiterone.py
jupiterone_pyoneer/relationships.py
jupiterone_pyoneer-0.2.2.dist-info/METADATA
jupiterone_pyoneer-0.2.2.dist-info/WHEEL
jupiterone_pyoneer-0.2.2.dist-info/top_level.txt
jupiterone_pyoneer-0.2.2.dist-info/RECORD
