Metadata-Version: 2.4
Name: jupiterone_pyoneer
Version: 0.2.2
Requires-Python: >=3.7
Requires-Dist: requests>=2.25.1
Requires-Dist: pydantic
Dynamic: requires-dist
Dynamic: requires-python
